README.rst
setup.py
MLFeatureSelection/FeatureSelection.py
MLFeatureSelection/__init__.py
MLFeatureSelection/check_length.py
MLFeatureSelection/coherence_selection.py
MLFeatureSelection/importance_selection.py
MLFeatureSelection/sequence_selection.py
MLFeatureSelection/tools.py
MLFeatureSelection/variance_selection.py
MLFeatureSelection.egg-info/PKG-INFO
MLFeatureSelection.egg-info/SOURCES.txt
MLFeatureSelection.egg-info/dependency_links.txt
MLFeatureSelection.egg-info/requires.txt
MLFeatureSelection.egg-info/top_level.txt