Metadata-Version: 1.1
Name: MLFeatureSelection
Version: 0.0.9.5.1
Summary: Features selection algorithm based on self selected algorithm, loss function and validation method
Home-page: https://github.com/duxuhao/Feature-Selection
Author: Xuhao(Peter) Du
Author-email: duxuhao88@gmail.com
License: MIT Licence
Keywords: pypi easy_install pip
Platform: Linux
Classifier: Programming Language :: Python
Classifier: Programming Language :: Python :: Implementation
Classifier: Programming Language :: Python :: 2
Classifier: Programming Language :: Python :: 2.7
Classifier: Programming Language :: Python :: 3
Classifier: Programming Language :: Python :: 3.4
Classifier: Programming Language :: Python :: 3.5
Classifier: Programming Language :: Python :: 3.6
Classifier: Topic :: Software Development :: Libraries
